<annotation>
	<folder>fracca</folder>
	<filename>000000073437.jpg</filename>
	<path>/Users/michelefraccaroli/Desktop/Dataset/fracca/000000073437.jpg</path>
	<source>
		<database>Unknown</database>
	</source>
	<size>
		<width>640</width>
		<height>443</height>
		<depth>3</depth>
	</size>
	<segmented>0</segmented>
	<object>
		<name>bike</name>
		<pose>Unspecified</pose>
		<truncated>0</truncated>
		<difficult>0</difficult>
		<bndbox>
			<xmin>156</xmin>
			<ymin>311</ymin>
			<xmax>215</xmax>
			<ymax>409</ymax>
		</bndbox>
	</object>
</annotation>
