<annotation>
	<folder>train</folder>
	<filename>497723672.jpg</filename>
	<path>/Users/michelefraccaroli/Desktop/ami_project/Dataset/train/497723672.jpg</path>
	<source>
		<database>Unknown</database>
	</source>
	<size>
		<width>500</width>
		<height>375</height>
		<depth>3</depth>
	</size>
	<segmented>0</segmented>
	<object>
		<name>bike</name>
		<pose>Unspecified</pose>
		<truncated>0</truncated>
		<difficult>0</difficult>
		<bndbox>
			<xmin>268</xmin>
			<ymin>172</ymin>
			<xmax>337</xmax>
			<ymax>313</ymax>
		</bndbox>
	</object>
	<object>
		<name>bike</name>
		<pose>Unspecified</pose>
		<truncated>0</truncated>
		<difficult>0</difficult>
		<bndbox>
			<xmin>198</xmin>
			<ymin>159</ymin>
			<xmax>258</xmax>
			<ymax>282</ymax>
		</bndbox>
	</object>
	<object>
		<name>bike</name>
		<pose>Unspecified</pose>
		<truncated>0</truncated>
		<difficult>0</difficult>
		<bndbox>
			<xmin>179</xmin>
			<ymin>157</ymin>
			<xmax>213</xmax>
			<ymax>247</ymax>
		</bndbox>
	</object>
</annotation>
