<annotation>
	<folder>train</folder>
	<filename>558124556.jpg</filename>
	<path>/Users/michelefraccaroli/Desktop/ami_project/Dataset/train/558124556.jpg</path>
	<source>
		<database>Unknown</database>
	</source>
	<size>
		<width>333</width>
		<height>500</height>
		<depth>3</depth>
	</size>
	<segmented>0</segmented>
	<object>
		<name>bike</name>
		<pose>Unspecified</pose>
		<truncated>1</truncated>
		<difficult>0</difficult>
		<bndbox>
			<xmin>2</xmin>
			<ymin>206</ymin>
			<xmax>194</xmax>
			<ymax>500</ymax>
		</bndbox>
	</object>
</annotation>
